laplace/__init__.py
laplace/__pycache__/__init__.d.er
laplace/baselaplace.py
laplace/curvature/__init__.py
laplace/curvature/asdfghjkl.py
laplace/curvature/asdl.py
laplace/curvature/backpack.py
laplace/curvature/curvature.py
laplace/curvature/curvlinops.py
laplace/laplace.py
laplace/lllaplace.py
laplace/marglik_training.py
laplace/py.typed
laplace/subnetlaplace.py
laplace/utils/__init__.py
laplace/utils/__pycache__/enums.d.er
laplace/utils/enums.py
laplace/utils/feature_extractor.py
laplace/utils/matrix.py
laplace/utils/metrics.py
laplace/utils/subnetmask.py
laplace/utils/swag.py
laplace/utils/utils.py
laplace_torch-0.2.2.2.dist-info/METADATA
laplace_torch-0.2.2.2.dist-info/WHEEL
laplace_torch-0.2.2.2.dist-info/entry_points.txt
laplace_torch-0.2.2.2.dist-info/licenses/LICENSE.txt
laplace_torch-0.2.2.2.dist-info/RECORD
