Metadata-Version: 2.1
Name: laplace-torch
Version: 0.2.2.2
Summary: laplace - Laplace approximations for deep learning
Author: Alex Immer, Runa Eschenhagen, Agustinus Kristiadi, Erik Daxberger
License: MIT
Classifier: Development Status :: 3 - Alpha
Classifier: License :: OSI Approved :: MIT License
Classifier: Operating System :: OS Independent
Classifier: Programming Language :: Python :: 3.9
Classifier: Programming Language :: Python :: 3.10
Classifier: Programming Language :: Python :: 3.11
Classifier: Programming Language :: Python :: 3.12
Project-URL: Homepage, https://github.com/aleximmer/Laplace
Project-URL: Bug Tracker, https://github.com/aleximmer/Laplace/issues
Requires-Python: >=3.9
Requires-Dist: asdfghjkl==0.1a4
Requires-Dist: backpack-for-pytorch
Requires-Dist: curvlinops-for-pytorch>=2.0
Requires-Dist: numpy
Requires-Dist: opt_einsum
Requires-Dist: torch>=2.0
Requires-Dist: torchmetrics
Requires-Dist: torchvision>=0.15
Provides-Extra: dev
Requires-Dist: coveralls; extra == "dev"
Requires-Dist: matplotlib; extra == "dev"
Requires-Dist: mkdocs; extra == "dev"
Requires-Dist: mkdocs-material; extra == "dev"
Requires-Dist: mkdocstrings-python; extra == "dev"
Requires-Dist: pytest; extra == "dev"
Requires-Dist: pytest-cov; extra == "dev"
Requires-Dist: pytest-mock; extra == "dev"
Requires-Dist: ruff; extra == "dev"
Requires-Dist: scipy; extra == "dev"
